radius_eap_mschapv2/EAPPacket.py
radius_eap_mschapv2/MSCHAPv2.py
radius_eap_mschapv2/RADIUS.py
radius_eap_mschapv2/__init__.py
test/__init__.py
test/testRADIUS.py
radius_eap_mschapv2_client-1.0.6.dist-info/LICENSE
radius_eap_mschapv2_client-1.0.6.dist-info/METADATA
radius_eap_mschapv2_client-1.0.6.dist-info/WHEEL
radius_eap_mschapv2_client-1.0.6.dist-info/top_level.txt
radius_eap_mschapv2_client-1.0.6.dist-info/RECORD
