Metadata-Version: 2.1
Name: radius-eap-mschapv2-client
Version: 1.0.6
Summary: A RADIUS EAP-MSCHAPv2 client
Home-page: https://github.com/mneitsabes/RADIUS-EAP-MSCHAPv2-Python-client
Author: mneitsabes
Author-email: mneitsabes@nulloz.be
License: UNKNOWN
Keywords: radius,EAP,MSCHAPv2
Platform: UNKNOWN
Classifier: Programming Language :: Python :: 3
Classifier: License :: OSI Approved :: MIT License
Classifier: Operating System :: OS Independent
Requires-Python: >=3.6
License-File: LICENSE
Requires-Dist: pycryptodome
